MANIFEST.in
README.rst
setup.cfg
setup.py
purge_old_files/__init__.py
purge_old_files/age.py
purge_old_files/cli.py
purge_old_files/filters.py
purge_old_files/finder.py
purge_old_files.egg-info/PKG-INFO
purge_old_files.egg-info/SOURCES.txt
purge_old_files.egg-info/dependency_links.txt
purge_old_files.egg-info/entry_points.txt
purge_old_files.egg-info/top_level.txt