Metadata-Version: 1.1
Name: purge-old-files
Version: 1.3.0
Summary: Purge old files using constraints
Home-page: https://github.com/pmuller/purge-old-files
Author: Philippe Muller
Author-email: philippe.muller@gmail.com
License: Apache License 2.0
Platform: UNKNOWN
Classifier: Programming Language :: Python :: 3.5
Classifier: Intended Audience :: Developers
Classifier: Development Status :: 5 - Production/Stable
Classifier: Operating System :: POSIX :: Linux
